odoo/addons/partner_contact_age_range/README.rst
odoo/addons/partner_contact_age_range/__init__.py
odoo/addons/partner_contact_age_range/__manifest__.py
odoo/addons/partner_contact_age_range/data/age_range_cron.xml
odoo/addons/partner_contact_age_range/i18n/partner_contact_age_range.pot
odoo/addons/partner_contact_age_range/models/__init__.py
odoo/addons/partner_contact_age_range/models/res_partner.py
odoo/addons/partner_contact_age_range/models/res_partner_age_range.py
odoo/addons/partner_contact_age_range/readme/CONTRIBUTORS.rst
odoo/addons/partner_contact_age_range/readme/DESCRIPTION.rst
odoo/addons/partner_contact_age_range/readme/USAGE.rst
odoo/addons/partner_contact_age_range/security/ir.model.access.csv
odoo/addons/partner_contact_age_range/static/description/age_range.png
odoo/addons/partner_contact_age_range/static/description/configure_age_range.png
odoo/addons/partner_contact_age_range/static/description/icon.png
odoo/addons/partner_contact_age_range/static/description/index.html
odoo/addons/partner_contact_age_range/tests/__init__.py
odoo/addons/partner_contact_age_range/tests/test_res_partner_age_range.py
odoo/addons/partner_contact_age_range/views/res_partner_age_range_view.xml
odoo/addons/partner_contact_age_range/views/res_partner_view.xml
odoo14_addon_partner_contact_age_range-14.0.1.0.1.dist-info/METADATA
odoo14_addon_partner_contact_age_range-14.0.1.0.1.dist-info/WHEEL
odoo14_addon_partner_contact_age_range-14.0.1.0.1.dist-info/top_level.txt
odoo14_addon_partner_contact_age_range-14.0.1.0.1.dist-info/RECORD
